{"13255":{"nama":"LUBUK ALUNG","dapil":[13,1302,11302,2130502]},"87282":{"nama":"PUNGGUANG KASIAK LUBUK ALUNG","dapil":[13,1302,11302,2130502]},"87283":{"nama":"PASIE LAWEH LUBUK ALUNG","dapil":[13,1302,11302,2130502]},"87285":{"nama":"AIE TAJUN LUBUK ALUNG","dapil":[13,1302,11302,2130502]},"87286":{"nama":"SIKABU LUBUK ALUNG","dapil":[13,1302,11302,2130502]},"931213":{"nama":"SUNGAI ABANG LUBUK ALUNG","dapil":[13,1302,11302,2130502]},"931214":{"nama":"SINGGULIANG LUBUK ALUNG","dapil":[13,1302,11302,2130502]},"931215":{"nama":"SALIBUTAN LUBUK ALUNG","dapil":[13,1302,11302,2130502]},"931216":{"nama":"BALAH HILIA LUBUK ALUNG","dapil":[13,1302,11302,2130502]}}