{"149":{"nama":"KEUDE TRUMON","dapil":[11,1101,11109,2110105]},"150":{"nama":"UJONG TANOH","dapil":[11,1101,11109,2110105]},"151":{"nama":"SIGLENG","dapil":[11,1101,11109,2110105]},"152":{"nama":"IE MEUDAMA","dapil":[11,1101,11109,2110105]},"153":{"nama":"TEUPIN TINGGI","dapil":[11,1101,11109,2110105]},"154":{"nama":"KUTA BARO","dapil":[11,1101,11109,2110105]},"155":{"nama":"PANTON BILIE","dapil":[11,1101,11109,2110105]},"157":{"nama":"KUTA PADANG","dapil":[11,1101,11109,2110105]},"158":{"nama":"RAKET","dapil":[11,1101,11109,2110105]},"159":{"nama":"PADANG HARAPAN","dapil":[11,1101,11109,2110105]},"160":{"nama":"SEUNEUBOK JAYA","dapil":[11,1101,11109,2110105]},"931268":{"nama":"GAMPONG TEUNGOH","dapil":[11,1101,11109,2110105]}}