{"62693":{"nama":"ANJIR SERAPAT MUARA","dapil":[63,6301,16303,2630404]},"62694":{"nama":"ANJIR MUARA KOTA","dapil":[63,6301,16303,2630404]},"62695":{"nama":"PATIH MUHUR","dapil":[63,6301,16303,2630404]},"62696":{"nama":"ANJIR MUARA KOTA TENGAH","dapil":[63,6301,16303,2630404]},"62697":{"nama":"ANJIR SERAPAT LAMA","dapil":[63,6301,16303,2630404]},"62698":{"nama":"ANJIR SERAPAT BARU","dapil":[63,6301,16303,2630404]},"62699":{"nama":"ANJIR MUARA LAMA","dapil":[63,6301,16303,2630404]},"62700":{"nama":"SUNGAI PUNGGU","dapil":[63,6301,16303,2630404]},"62701":{"nama":"ANJIR SERAPAT BARU I","dapil":[63,6301,16303,2630404]},"62702":{"nama":"PATIH MUHUR BARU","dapil":[63,6301,16303,2630404]},"62703":{"nama":"SEI PUNGGU BARU","dapil":[63,6301,16303,2630404]},"62704":{"nama":"ANJIR SERAPAT MUARA I","dapil":[63,6301,16303,2630404]},"62705":{"nama":"SEPAKAT BARSAMA","dapil":[63,6301,16303,2630404]},"62706":{"nama":"MARABAHAN BARU","dapil":[63,6301,16303,2630404]},"62707":{"nama":"BERINGIN JAYA","dapil":[63,6301,16303,2630404]}}