{"6580":{"nama":"BATUPHAT BARAT","dapil":[11,1102,11105,2117304]},"6581":{"nama":"UJONG PACU","dapil":[11,1102,11105,2117304]},"6582":{"nama":"BLANG NALEUNG MAMEH","dapil":[11,1102,11105,2117304]},"6583":{"nama":"BATUPHAT TIMUR","dapil":[11,1102,11105,2117304]},"6584":{"nama":"BLANG PULO","dapil":[11,1102,11105,2117304]},"6585":{"nama":"PADANG SAKTI","dapil":[11,1102,11105,2117304]},"6586":{"nama":"COT TRIENG","dapil":[11,1102,11105,2117304]},"6587":{"nama":"PALOH PUNTI","dapil":[11,1102,11105,2117304]},"6588":{"nama":"MEUNASAH DAYAH","dapil":[11,1102,11105,2117304]},"6589":{"nama":"MEURIA PALOH","dapil":[11,1102,11105,2117304]},"6590":{"nama":"BLANG PANYANG","dapil":[11,1102,11105,2117304]}}