{"7267":{"nama":"SIMARPINGGAN","dapil":[12,1202,11209,2120104]},"7268":{"nama":"PARGARINGAN","dapil":[12,1202,11209,2120104]},"7300":{"nama":"P.O. HURLANG","dapil":[12,1202,11209,2120104]},"7301":{"nama":"KOLANG NAULI","dapil":[12,1202,11209,2120104]},"7302":{"nama":"UNTE MUNGKUR IV","dapil":[12,1202,11209,2120104]},"7303":{"nama":"UNTE MUNGKUR III","dapil":[12,1202,11209,2120104]},"7304":{"nama":"UNTE MUNGKUR II","dapil":[12,1202,11209,2120104]},"7305":{"nama":"UNTE MUNGKUR I","dapil":[12,1202,11209,2120104]},"7306":{"nama":"SATAHI NAULI","dapil":[12,1202,11209,2120104]},"7307":{"nama":"HURLANG MUARA NAULI","dapil":[12,1202,11209,2120104]},"7308":{"nama":"SIPAKPAHI AEK LOBU","dapil":[12,1202,11209,2120104]},"7309":{"nama":"HODOPA NAULI","dapil":[12,1202,11209,2120104]},"7310":{"nama":"MAKARTI NAULI","dapil":[12,1202,11209,2120104]},"7311":{"nama":"RAWA MAKMUR","dapil":[12,1202,11209,2120104]}}