{"12929":{"nama":"INDERAPURA TIMUR","dapil":[13,1301,11308,2130105]},"12930":{"nama":"INDERAPURA UTARA","dapil":[13,1301,11308,2130105]},"84398":{"nama":"MUARA INDERAPURA","dapil":[13,1301,11308,2130105]},"84399":{"nama":"DAMAR LAPAN BATANG INDERAPURA","dapil":[13,1301,11308,2130105]},"84400":{"nama":"LALANG PANJANG INDERAPURA","dapil":[13,1301,11308,2130105]},"84401":{"nama":"PALOKAN INDERAPURA","dapil":[13,1301,11308,2130105]},"84402":{"nama":"LUBUK BETUNG INDERAPURA","dapil":[13,1301,11308,2130105]},"84403":{"nama":"TLUK KUALO INDERAPURA","dapil":[13,1301,11308,2130105]},"84404":{"nama":"TANAH BAKALI INDERAPURA","dapil":[13,1301,11308,2130105]},"84405":{"nama":"PULAU RAJO INDERAPURA","dapil":[13,1301,11308,2130105]}}